README.rst
setup.py
django_concurrent_test_helper.egg-info/PKG-INFO
django_concurrent_test_helper.egg-info/SOURCES.txt
django_concurrent_test_helper.egg-info/dependency_links.txt
django_concurrent_test_helper.egg-info/requires.txt
django_concurrent_test_helper.egg-info/top_level.txt
django_concurrent_tests/__about__.py
django_concurrent_tests/__init__.py
django_concurrent_tests/b64pickle.py
django_concurrent_tests/errors.py
django_concurrent_tests/helpers.py
django_concurrent_tests/utils.py
django_concurrent_tests/management/__init__.py
django_concurrent_tests/management/commands/__init__.py
django_concurrent_tests/management/commands/concurrent_call_wrapper.py