Metadata-Version: 1.1
Name: django-concurrent-test-helper
Version: 0.6.3
Summary: Helpers for executing Django app code concurrently within Django tests
Home-page: https://github.com/depop/django-concurrent-test-helper
Author: Anentropic
Author-email: ego@anentropic.com
License: Apache 2.0
Platform: UNKNOWN
Classifier: Environment :: Web Environment
Classifier: Intended Audience :: Developers
Classifier: License :: OSI Approved :: Apache Software License
Classifier: Operating System :: OS Independent
Classifier: Programming Language :: Python
Classifier: Framework :: Django
